pyaimp.py
pyaimp-0.2.3.dist-info/DESCRIPTION.rst
pyaimp-0.2.3.dist-info/METADATA
pyaimp-0.2.3.dist-info/RECORD
pyaimp-0.2.3.dist-info/WHEEL
pyaimp-0.2.3.dist-info/metadata.json
pyaimp-0.2.3.dist-info/top_level.txt
