Metadata-Version: 1.1
Name: pyaimp
Version: 0.2.3
Summary: Python AIMP remote API wrapper with some extras
Home-page: https://github.com/EpocDotFr/pyaimp
Author: Maxime "Epoc" G.
Author-email: contact.nospam@epoc.nospam.fr
License: DBAD
Download-URL: https://github.com/EpocDotFr/pyaimp/archive/pyaimp-0.2.3.tar.gz
Keywords: aimp remote api wrapper client
Platform: UNKNOWN
Classifier: Development Status :: 4 - Beta
Classifier: Intended Audience :: Developers
Classifier: Topic :: Software Development :: Libraries
Classifier: Programming Language :: Python
Classifier: Programming Language :: Python :: 3.5
Classifier: Operating System :: Microsoft :: Windows
